xbc/__init__.py
xbc/utils.py
xbc/version.py
py_xbc-0.1.2.dist-info/LICENSE.txt
py_xbc-0.1.2.dist-info/METADATA
py_xbc-0.1.2.dist-info/WHEEL
py_xbc-0.1.2.dist-info/top_level.txt
py_xbc-0.1.2.dist-info/RECORD
