Metadata-Version: 2.1
Name: py-xbc
Version: 0.1.2
Summary: A library for manipulating eXtra BootConfig (XBC) files
Author-email: Síle Ekaterin Liszka <sheila@vulpine.house>
Project-URL: Homepage, https://gitea.treehouse.systems/VulpineAmethyst/py-xbc
Project-URL: Issues, https://gitea.treehouse.systems/VulpineAmethyst/py-xbc/issues
Keywords: bootconfig,xbc,configuration
Classifier: Development Status :: 4 - Beta
Classifier: Intended Audience :: Developers
Classifier: License :: OSI Approved :: MIT License
Classifier: Operating System :: OS Independent
Classifier: Programming Language :: Python :: 3
Classifier: Programming Language :: Python :: 3.7
Classifier: Programming Language :: Python :: 3.8
Classifier: Programming Language :: Python :: 3.9
Classifier: Programming Language :: Python :: 3.10
Classifier: Programming Language :: Python :: 3.11
Classifier: Programming Language :: Python :: 3.12
Classifier: Topic :: Utilities
Requires-Python: >=3.7
License-File: LICENSE.txt
Requires-Dist: pyparsing
Provides-Extra: test
Requires-Dist: pytest ; extra == 'test'
